[

  {
    "title": "Fuchsia 是什么？Fuchsia OS 的未来如何？",
    "url": "https://juejin.im/post/5e5dfac751882549422ee02f",
    "author": "恋猫de小郭"
  },
  {
    "title": "我们和 Flutter Create 全球大奖得主喝了一杯功夫茶",
    "url": "https://mp.weixin.qq.com/s/_YyZolOj3XOv235psOT5pQ",
    "author": "公众号【谷歌开发者】"
  },
  {
    "title": "5KB 代码创乾坤！快来感受下 Flutter 的美妙与潜力！",
    "url": "https://mp.weixin.qq.com/s/VOJnNlR1Eg3wEvNSlv4c1Q",
    "author": "公众号【谷歌开发者】"
  },
  {
    "title": "Dart 2.7 发布: 更安全、更具表现力的 Dart",
    "url": "https://mp.weixin.qq.com/s/aWLdZC6EWqokEFlQONHyAg",
    "author": "公众号【谷歌开发者】"
  },
  {
    "title": "Flutter: 首个面向环境计算打造的 UI 平台",
    "url": "https://mp.weixin.qq.com/s/ItRWmXPKt81tKLLTWoJqEQ",
    "author": "公众号【谷歌开发者】"
  },
  {
    "title": "Flutter 1.12 正式发布，为这一年画上圆满的句号！",
    "url": "https://mp.weixin.qq.com/s/sETtUi-J4cxCCbKP_FQkpA",
    "author": "公众号【谷歌开发者】"
  },
  {
    "title": "Flutter 智能闹钟挑战赛约你来战！",
    "url": "https://mp.weixin.qq.com/s/mp2XxbP1jfsayw6oVEjb2Q",
    "author": "公众号【谷歌开发者】"
  },
  {
    "title": "Dart 2.5 正式公布",
    "url": "https://mp.weixin.qq.com/s/WiOrnFLauZe2ppKsK04JCQ",
    "author": "公众号【谷歌开发者】"
  },
  {
    "title": "Flutter 1.9 正式发布！| 全平台创新开发体验",
    "url": "https://mp.weixin.qq.com/s/uajbjbVYmcBHtq3Jv8tgzg",
    "author": "公众号【谷歌开发者】"
  },
  {
    "title": "Flutter 为您的 Web 应用开发注入更多精彩",
    "url": "https://mp.weixin.qq.com/s/trNhd1CI1gBBDtmVGdeI6g",
    "author": "公众号【谷歌开发者】"
  },
  {
    "title": "Flutter 1.7 正式发布",
    "url": "https://mp.weixin.qq.com/s/GONNr2_pswHmBGET_weOdA",
    "author": "公众号【谷歌开发者】"
  },
  {
    "title": "Flutter 官方做了一款游戏，开源的",
    "url": "https://mp.weixin.qq.com/s/iC3HvgkkHLNa-kbEonXPLA",
    "author": "公众号【谷歌开发者】"
  },
  {
    "title": "Flutter 与 Chrome OS 珠联璧合",
    "url": "https://mp.weixin.qq.com/s/umWTwk9retPvPgRNJaNvPA",
    "author": "公众号【谷歌开发者】"
  },
  {
    "title": "Flutter 2019 产品路线图",
    "url": "https://mp.weixin.qq.com/s/aRhQdMd0R74adph9_V0wgQ",
    "author": "公众号【谷歌开发者】"
  },
  {
    "title": "Flutter 1.0 正式版: Google 的便携 UI 工具包",
    "url": "https://mp.weixin.qq.com/s/hCIN42OMmmc6HkOveegwWQ",
    "author": "公众号【谷歌开发者】"
  }
]